pipzh/__init__.py
pipzh/main.py
pipzh-20260107.dist-info/licenses/LICENSE
pipzh-20260107.dist-info/METADATA
pipzh-20260107.dist-info/WHEEL
pipzh-20260107.dist-info/entry_points.txt
pipzh-20260107.dist-info/top_level.txt
pipzh-20260107.dist-info/RECORD
