Metadata-Version: 2.4
Name: pipzh
Version: 20260107
Summary: A simple wrapper for pip to use Tsinghua mirror automatically.
Author: qiziAI
Requires-Python: >=3.8
License-File: LICENSE
Dynamic: license-file
